app_info.py
canvas_view.py
constants.py
export_drawsvg.py
import_drawsvg.py
main.py
main_window.py
palette.py
properties_panel.py
drawsvg_ui-0.5.5.dist-info/licenses/LICENSE
items/__init__.py
items/base.py
items/labels.py
items/text.py
items/shapes/__init__.py
items/shapes/curves.py
items/shapes/lines.py
items/shapes/polygons.py
items/shapes/rects.py
items/widgets/__init__.py
items/widgets/folder_tree.py
ui/__init__.py
ui/main_window.ui
ui/properties_panel.ui
drawsvg_ui-0.5.5.dist-info/METADATA
drawsvg_ui-0.5.5.dist-info/WHEEL
drawsvg_ui-0.5.5.dist-info/entry_points.txt
drawsvg_ui-0.5.5.dist-info/top_level.txt
drawsvg_ui-0.5.5.dist-info/RECORD
