Metadata-Version: 2.4
Name: drawsvg-ui
Version: 0.5.5
Summary: GUI for creating drawsvg scenes with PySide6
Author-email: Taron686 <Taron686@users.noreply.github.com>
License: GPL-3.0-or-later
Project-URL: Homepage, https://github.com/Taron686/drawsvg-ui
Project-URL: Repository, https://github.com/Taron686/drawsvg-ui
Project-URL: Documentation, https://github.com/Taron686/drawsvg-ui#readme
Project-URL: Issue Tracker, https://github.com/Taron686/drawsvg-ui/issues
Keywords: drawsvg,pyside6,gui,svg,vector-graphics,editor
Classifier: Development Status :: 4 - Beta
Classifier: Environment :: X11 Applications :: Qt
Classifier: Intended Audience :: End Users/Desktop
Classifier: License :: OSI Approved :: GNU General Public License v3 or later (GPLv3+)
Classifier: Operating System :: OS Independent
Classifier: Programming Language :: Python :: 3 :: Only
Classifier: Programming Language :: Python :: 3.10
Classifier: Programming Language :: Python :: 3.11
Classifier: Programming Language :: Python :: 3.12
Classifier: Topic :: Multimedia :: Graphics :: Editors
Classifier: Topic :: Multimedia :: Graphics :: Viewers
Classifier: Topic :: Software Development :: User Interfaces
Requires-Python: >=3.10
License-File: LICENSE
Requires-Dist: drawsvg<3,>=2.4
Requires-Dist: PySide6<7,>=6.9.2
Requires-Dist: PySide6-Addons<7,>=6.9.2
Requires-Dist: PySide6-Essentials<7,>=6.9.2
Requires-Dist: shiboken6<7,>=6.9.2
Dynamic: license-file
